[{"type":"interface","name":"TableFormConfig","description":"<p>nzx-table-form 配置项</p>\n","properties":[{"name":"header","type":"string","default":"null","description":"<p>表头名</p>\n"},{"name":"width","type":"string","default":"null","description":"<p>可选，td th 宽度</p>\n"},{"name":"controlName","type":"string","default":"null","description":"<p>控件字段名</p>\n"},{"name":"defaultValue","type":"string","default":"null","description":"<p>可选，控件默认值</p>\n"},{"name":"type","type":"'input' | 'date' | 'select' | 'number' | 'radio' | 'textarea' | 'template'","default":"null","description":"<p>可选，控件类型</p>\n"},{"name":"validation","type":"Array<any>","default":"null","description":"<p>可选 控件校验</p>\n"},{"name":"errorTip","type":"string","default":"null","description":"<p>可选 控件错误提示</p>\n"},{"name":"options","type":"Array<Options<any>>","default":"null","description":"<p>可选 控件为select radio时下拉选项</p>\n"},{"name":"controlMode","type":"'readonly' | 'edit'","default":"edit","description":"<p>可选 控件模式</p>\n"},{"name":"isShow","type":"boolean","default":"true","description":"<p>可选 控件列是否在table中展示</p>\n"},{"name":"placeholder","type":"string","default":"请输入","description":"<p>可选 placeholder</p>\n"},{"name":"allowClear","type":"boolean","description":"<p>可选 select时，是否允许清空</p>\n"},{"name":"showRequiredTip","type":"boolean","description":"<p>可选 th是否展示必填星号</p>\n"},{"name":"templateRef","type":"TemplateRef<unknown>","description":"<p>可选 自定义模板</p>\n"},{"name":"maxLength","type":"string | number","description":"<p>可选 最大字符长度</p>\n"},{"name":"max","type":"number","description":"<p>可选 nz-input-number时max</p>\n"},{"name":"format","type":"(value: any) => any","description":"<p>可选 readonly时自定义函数用来自定义展示</p>\n"}]},{"type":"interface","name":"LimitMessage","description":"<p>启用数量限制时的警告信息</p>\n","properties":[{"name":"type","type":"'max' | 'min'","default":"null","description":"<p>信息类型</p>\n"},{"name":"limit","type":"number","default":"null","description":"<p>限制数量</p>\n"},{"name":"msg","type":"string","default":"null","description":"<p>警告信息</p>\n"}]},{"type":"component","name":"nzx-table-form","description":"<p>表格表单。整个table为一个表单控件，适合当填写的表单为一个list集合的情况，支持自定义</p>\n","properties":[{"name":"tableLayout","type":"NzTableLayout","default":"fixed","description":"<p>fixed等宽</p>\n"},{"name":"tableAlign","type":"'left' | 'right' | 'center' | null","default":"center","description":"<p>table各项对齐方式</p>\n"},{"name":"enableExpand","type":"boolean","default":"false","description":"<p>table 启用扩展行</p>\n"},{"name":"nzxBordered","type":"boolean","default":"false","description":"<p>table border</p>\n"},{"name":"nzxSize","type":"NzTableSize","default":"default","description":"<p>table size</p>\n"},{"name":"enableLimit","type":"boolean","default":"false","description":"<p>启用数量限制</p>\n"},{"name":"maxLimit","type":"number","default":"0","description":"<p>最大数量</p>\n"},{"name":"minLimit","type":"number","default":"0","description":"<p>最小数量</p>\n"},{"name":"nzxFooter","type":"string | TemplateRef<void>","description":"<p>自定义footer</p>\n"},{"name":"errorTemplate","type":"TemplateRef<void>","description":"<p>校验整个table错误提示的自定义模板</p>\n"},{"name":"enableNo","type":"boolean","default":"false","description":"<p>启用序号</p>\n"},{"name":"serialNumberWidth","type":"string","default":"60px","description":"<p>序号列宽度</p>\n"},{"name":"serialNumberTemplate","type":"TemplateRef<void>","description":"<p>序号自定义模板</p>\n"},{"name":"tableValidatorFn","type":"ValidatorFn","default":"(control: AbstractControl): ValidationErrors | null => null","description":"<p>校验table的函数</p>\n"},{"name":"tableFormConfig","type":"TableFormConfig[]","default":"[]","description":"<p>table config</p>\n"},{"name":"limitMessage","type":"EventEmitter<LimitMessage>","default":"[]","description":"<p>数量限制消息回调</p>\n"}]},{"type":"directive","name":"nzxTableFormTd","description":"<p>用来自定用td</p>\n","properties":[{"name":"templateRef","type":"TemplateRef<unknown>","default":"undefined","description":"<div class=\"dg-paragraph\"><code>&lt;ng-template&gt;&lt;/ng-template&gt;</code>上使用</div>\n"},{"name":"controlName","type":"string","default":"undefined","description":"<div class=\"dg-paragraph\"><code>&lt;ng-template&gt;&lt;/ng-template&gt;</code>上使用,当此td为一个表单控件时需要传入controlName</div>\n"}]},{"type":"directive","name":"nzxTableFormTh","description":"<p>用来自定义th</p>\n","properties":[{"name":"width","type":"string | null","default":"null","description":"<p>th的宽度</p>\n"},{"name":"templateRef","type":"TemplateRef<unknown>","default":"undefined","description":"<div class=\"dg-paragraph\"><code>&lt;ng-template&gt;&lt;/ng-template&gt;</code>上使用</div>\n"}]},{"type":"directive","name":"nzxTableFormExpand","description":"<p>用来支持自定义行拓展</p>\n","properties":[{"name":"templateRef","type":"TemplateRef<unknown>","default":"undefined","description":"<div class=\"dg-paragraph\"><code>&lt;ng-template&gt;&lt;/ng-template&gt;</code>上使用</div>\n"}]}]